general_tools/__init__.py
general_tools/file_utils.py
general_tools/git_wrapper.py
general_tools/languages.py
general_tools/print_utils.py
general_tools/smartquotes.py
general_tools/url_utils.py
uw/__init__.py
uw/update_catalog.py
uw_tools-0.0.6.dist-info/DESCRIPTION.rst
uw_tools-0.0.6.dist-info/METADATA
uw_tools-0.0.6.dist-info/RECORD
uw_tools-0.0.6.dist-info/WHEEL
uw_tools-0.0.6.dist-info/metadata.json
uw_tools-0.0.6.dist-info/top_level.txt
