Metadata-Version: 2.0
Name: uw-tools
Version: 0.0.6
Summary: A collection of useful scripts
Home-page: https://github.org/unfoldingWord-dev/uw_tools
Author: unfoldingWord
Author-email: phillip_hopper@wycliffeassociates.org
License: MIT
Keywords: unfoldingWord python tools
Platform: UNKNOWN
Requires: pygithub
Requires: pyparsing
